Metadata-Version: 2.1
Name: bookend_rna
Version: 1.1.0
Summary: End-guided transcript assembler for short and long RNA-seq reads.
Home-page: https://github.com/Gregor-Mendel-Institute/bookend
Author: Michael A. Schon
Author-email: michael.schon@wur.nl
License: UNKNOWN
Keywords: transcriptome assembler bioinformatics rna sequencing
Platform: UNKNOWN
Classifier: Programming Language :: Python :: 3
Classifier: License :: OSI Approved :: MIT License
Classifier: Operating System :: OS Independent
Requires-Python: >=3.6
License-File: LICENSE
